{
    "attributes":  [
                       {
                           "type":  "minecraft:attack_damage",
                           "modifier":  {
                                            "name":  "tiered:epic_melee_weapons_attack_damage",
                                            "operation":  "ADD_MULTIPLIED_BASE",
                                            "amount":  0.08
                                        },
                           "optional_equipment_slots":  [
                                                            "MAINHAND"
                                                        ]
                       },
                       {
                           "type":  "tiered:generic.critical_chance",
                           "modifier":  {
                                            "name":  "tiered:epic_melee_weapons_critical_chance",
                                            "operation":  "ADD_VALUE",
                                            "amount":  0.3
                                        },
                           "optional_equipment_slots":  [
                                                            "MAINHAND"
                                                        ]
                       },
                       {
                           "type":  "tiered:generic.critical_damage",
                           "modifier":  {
                                            "name":  "tiered:epic_melee_weapons_critical_damage",
                                            "operation":  "ADD_MULTIPLIED_BASE",
                                            "amount":  0.45
                                        },
                           "optional_equipment_slots":  [
                                                            "MAINHAND"
                                                        ]
                       },
                       {
                           "type":  "tiered:generic.looting",
                           "modifier":  {
                                            "name":  "tiered:epic_melee_weapons_looting",
                                            "operation":  "ADD_MULTIPLIED_BASE",
                                            "amount":  0.08
                                        },
                           "optional_equipment_slots":  [
                                                            "MAINHAND"
                                                        ]
                       },
                       {
                           "type":  "tiered:generic.sweeping_range",
                           "modifier":  {
                                            "name":  "tiered:epic_melee_weapons_sweeping_range",
                                            "operation":  "ADD_MULTIPLIED_BASE",
                                            "amount":  0.08
                                        },
                           "optional_equipment_slots":  [
                                                            "MAINHAND"
                                                        ]
                       },
                       {
                           "type":  "tiered:generic.durability",
                           "modifier":  {
                                            "name":  "tiered:epic_melee_weapons_durability",
                                            "operation":  "ADD_MULTIPLIED_BASE",
                                            "amount":  0.2
                                        },
                           "optional_equipment_slots":  [
                                                            "MAINHAND"
                                                        ]
                       },
                       {
                           "type":  "tiered:generic.mastery",
                           "modifier":  {
                                            "name":  "tiered:epic_melee_weapons_mastery",
                                            "operation":  "ADD_MULTIPLIED_BASE",
                                            "amount":  0.12
                                        },
                           "optional_equipment_slots":  [
                                                            "MAINHAND"
                                                        ]
                       }
                   ]
}
